setup.py
rova_afval/__init__.py
rova_afval.egg-info/PKG-INFO
rova_afval.egg-info/SOURCES.txt
rova_afval.egg-info/dependency_links.txt
rova_afval.egg-info/top_level.txt