Metadata-Version: 1.1
Name: rova-afval
Version: 0.2
Summary: ROVA Afvalkalender API
Home-page: https://github.com/mlowijs/rova_afval
Author: M. Lowijs
Author-email: mlowijs@gmail.com
License: UNKNOWN
Download-URL: https://github.com/mlowijs/rova_afval/archive/0.2.tar.gz
Keywords: rova,afval
Platform: UNKNOWN
